{
    "version": 1,
    "revision": 0,
    "rules": [
        {
            "primary-output": "Engine\\x64\\Debug\\Singleton.obj",
            "outputs": [
                "Engine\\x64\\Debug\\Singleton.h_5CB849E7F5924E4.ifc.dt.module.json",
                "Engine\\x64\\Debug\\Singleton.h_5CB849E7F5924E4.ifc.dt.d.json",
                "Engine\\x64\\Debug\\Singleton.h.ifc"
            ],
            "provides": [
                {
                    "logical-name": "C:\\Users\\Sacha\\Documents\\GitHub\\Engine\\Singleton.h",
                    "source-path": "c:\\users\\sacha\\documents\\github\\engine\\singleton.h",
                    "lookup-method": "absolute"
                }
            ],
            "requires": []
        }
    ]
}